RSIPI/__init__.py
RSIPI/config_parser.py
RSIPI/echo_server_gui.py
RSIPI/inject_rsi_to_krl.py
RSIPI/krl_to_csv_parser.py
RSIPI/kuka_visualiser.py
RSIPI/live_plotter.py
RSIPI/network_handler.py
RSIPI/rsi_api.py
RSIPI/rsi_cli.py
RSIPI/rsi_client.py
RSIPI/rsi_config.py
RSIPI/rsi_echo_server.py
RSIPI/rsi_graphing.py
RSIPI/rsi_limit_parser.py
RSIPI/safety_manager.py
RSIPI/static_plotter.py
RSIPI/trajectory_planner.py
RSIPI/xml_handler.py
rsipi-0.1.0.dist-info/licenses/LICENSE
rsipi-0.1.0.dist-info/METADATA
rsipi-0.1.0.dist-info/WHEEL
rsipi-0.1.0.dist-info/top_level.txt
rsipi-0.1.0.dist-info/RECORD
