Metadata-Version: 2.4
Name: RSIPI
Version: 0.1.0
Summary: Robot Sensor Interface Python Integration (RSIPI) for KUKA RSI control
Author: YAdam Morgan
Author-email: Adam Morgan <yadam.j.morgan@swansea.ac.uk>
License: GNU AFFERO GENERAL PUBLIC LICENSE
Classifier: Programming Language :: Python :: 3
Classifier: License :: OSI Approved :: MIT License
Classifier: Operating System :: OS Independent
Requires-Python: >=3.8
License-File: LICENSE
Requires-Dist: pandas>=2.0
Requires-Dist: numpy>=1.22
Requires-Dist: matplotlib>=3.5
Requires-Dist: lxml>=4.9
Requires-Dist: scipy>=1.8
Dynamic: author
Dynamic: license-file
Dynamic: requires-python
